neutompy/__init__.py
neutompy/version.py
neutompy/image/__init__.py
neutompy/image/image.py
neutompy/image/rebin.py
neutompy/metrics/__init__.py
neutompy/metrics/metrics.py
neutompy/misc/__init__.py
neutompy/misc/uitools.py
neutompy/postproc/__init__.py
neutompy/postproc/convert.py
neutompy/postproc/crop.py
neutompy/preproc/__init__.py
neutompy/preproc/preproc.py
neutompy/recon/__init__.py
neutompy/recon/optomo.py
neutompy/recon/recon.py
neutompy/recon/mrfbp/__init__.py
neutompy/recon/mrfbp/astra_plugin.py
neutompy/recon/nnfbp/TrainingData.py
neutompy/recon/nnfbp/__init__.py
neutompy/recon/nnfbp/astra_plugin.py
neutompy-1.0.10.dist-info/LICENSE
neutompy-1.0.10.dist-info/METADATA
neutompy-1.0.10.dist-info/WHEEL
neutompy-1.0.10.dist-info/top_level.txt
neutompy-1.0.10.dist-info/RECORD
