Metadata-Version: 2.1
Name: neutompy
Version: 1.0.10
Summary: Python package for tomographic data processing and reconstruction
Home-page: https://github.com/dmici/NeuTomPy-toolbox
Author: Davide Micieli
Author-email: neutompy@gmail.com
License: UNKNOWN
Platform: UNKNOWN
Classifier: Programming Language :: Python :: 3
Classifier: Intended Audience :: Science/Research
Classifier: License :: OSI Approved :: GNU General Public License v3 (GPLv3)
Classifier: Intended Audience :: Science/Research
Classifier: Intended Audience :: Education
Classifier: Intended Audience :: Developers
Classifier: Natural Language :: English
Classifier: Operating System :: OS Independent
